gradio_medical_image_analyzer/__init__.py
gradio_medical_image_analyzer/fat_segmentation.py
gradio_medical_image_analyzer/medical_image_analyzer.py
gradio_medical_image_analyzer/medical_image_analyzer.pyi
gradio_medical_image_analyzer/xray_analyzer.py
gradio_medical_image_analyzer/templates/component.py
gradio_medical_image_analyzer/templates/component/index.js
gradio_medical_image_analyzer/templates/component/style.css
gradio_medical_image_analyzer/templates/example/index.js
gradio_medical_image_analyzer/templates/example/style.css
gradio_medical_image_analyzer-0.1.0.dist-info/METADATA
gradio_medical_image_analyzer-0.1.0.dist-info/WHEEL
gradio_medical_image_analyzer-0.1.0.dist-info/RECORD
