Metadata-Version: 2.4
Name: gradio_medical_image_analyzer
Version: 0.1.0
Summary: AI-agent optimized medical image analysis component for Gradio with DICOM support
Project-URL: repository, https://github.com/thedatadudech/gradio-medical-image-analyzer
Project-URL: documentation, https://github.com/thedatadudech/gradio-medical-image-analyzer#readme
Project-URL: issues, https://github.com/thedatadudech/gradio-medical-image-analyzer/issues
Project-URL: space, https://huggingface.co/spaces/AbdullahIsaMarkus/gradio_medical_image_analyzer
Author-email: Markus Clauss Vetsuisse Uni Zurich <markus@data-and-ai-dude.ch>
License: Apache-2.0
Keywords: ai-agents,ct-scan,dicom,fat-segmentation,gradio-custom-component,gradio-template-MedicalImageAnalyzer,hackathon-2025,image-analysis,medical-ai,medical-imaging,veterinary,x-ray
Classifier: Development Status :: 3 - Alpha
Classifier: Intended Audience :: Developers
Classifier: Intended Audience :: Healthcare Industry
Classifier: Intended Audience :: Science/Research
Classifier: License :: OSI Approved :: Apache Software License
Classifier: Operating System :: OS Independent
Classifier: Programming Language :: Python :: 3
Classifier: Programming Language :: Python :: 3 :: Only
Classifier: Programming Language :: Python :: 3.8
Classifier: Programming Language :: Python :: 3.9
Classifier: Programming Language :: Python :: 3.10
Classifier: Programming Language :: Python :: 3.11
Classifier: Programming Language :: Python :: 3.12
Classifier: Topic :: Scientific/Engineering :: Artificial Intelligence
Classifier: Topic :: Scientific/Engineering :: Image Processing
Classifier: Topic :: Scientific/Engineering :: Medical Science Apps.
Classifier: Topic :: Software Development :: Libraries :: Python Modules
Requires-Python: >=3.8
Requires-Dist: gradio<6.0,>=4.0
Requires-Dist: numpy>=1.21.0
Requires-Dist: opencv-python>=4.5.0
Requires-Dist: pillow>=10.0.0
Requires-Dist: pydicom>=2.3.0
Requires-Dist: scikit-image>=0.19.0
Requires-Dist: scipy>=1.7.0
Provides-Extra: dev
Requires-Dist: build; extra == 'dev'
Requires-Dist: twine; extra == 'dev'
